README.txt
setup.cfg
setup.py
PasteCall.egg-info/PKG-INFO
PasteCall.egg-info/SOURCES.txt
PasteCall.egg-info/dependency_links.txt
PasteCall.egg-info/entry_points.txt
PasteCall.egg-info/namespace_packages.txt
PasteCall.egg-info/requires.txt
PasteCall.egg-info/top_level.txt
PasteCall.egg-info/zip-safe
paste/__init__.py
paste/call/__init__.py
paste/call/commands.py