Metadata-Version: 1.0
Name: PasteCall
Version: 0.2
Summary: Paste entry point caller
Home-page: www.idiles.com
Author: Linas Juskevicius
Author-email: linas@idiles.com
License: MIT
Keywords: paste call entry point entrypoint entry_point deploy console
Platform: UNKNOWN
